pod/__init__.py
py_pod-2.0.3.dist-info/COPYING
py_pod-2.0.3.dist-info/COPYING.LESSER
py_pod-2.0.3.dist-info/METADATA
py_pod-2.0.3.dist-info/WHEEL
py_pod-2.0.3.dist-info/RECORD
