Metadata-Version: 2.1
Name: py-pod
Version: 2.0.3
Summary: Implementation of a Proper Orthogonal Decomposition (POD) method
Author: Christophe
Author-email: christophe.alexandre@pm.me
Requires-Python: >=3.10,<4.0
Classifier: Programming Language :: Python :: 3
Classifier: Programming Language :: Python :: 3.10
Classifier: Programming Language :: Python :: 3.11
Requires-Dist: nose2 (>=0.13.0,<0.14.0)
Requires-Dist: numpy (>=1.25.2,<2.0.0)
Requires-Dist: pydoctor (>=23.4.1,<24.0.0)
